{
    "data": [
      {
        "id": 1,
        "exerciseId": 1,
        "title": "Yoga for Pelvic Floor Strength",
        "imageUrl": "./assets/images/exercise/yoga_1.png",
        "description": "",
        "duration": 14
      },
      {
        "id": 2,
        "exerciseId": 1,
        "title": "Yoga for Balance and Coordination",
        "imageUrl": "./assets/images/exercise/yoga_2.png",
        "description": "",
        "duration": 14
      },
      {
        "id": 3,
        "exerciseId": 1,
        "title": "Yoga Ball Workouts",
        "imageUrl": "./assets/images/exercise/yoga_3.png",
        "description": "",
        "duration": 14
      }
    ]
  }